ski_lint/__init__.py
ski_lint/cli.py
ski_lint/utils.py
ski_lint-0.3.1.dist-info/LICENSE
ski_lint-0.3.1.dist-info/METADATA
ski_lint-0.3.1.dist-info/WHEEL
ski_lint-0.3.1.dist-info/entry_points.txt
ski_lint-0.3.1.dist-info/RECORD
