Metadata-Version: 2.1
Name: ski-lint
Version: 0.3.1
Summary: A pre-commit hook, that enforces ASCII content.
Home-page: https://github.com/svdimchenko/ski-lint/
License: MIT
Author: Serhii Dimchenko
Author-email: svdimchenko@gmail.com
Requires-Python: >=3.9
Classifier: Development Status :: 4 - Beta
Classifier: License :: OSI Approved :: MIT License
Classifier: Programming Language :: Python
Classifier: Programming Language :: Python :: 3
Classifier: Programming Language :: Python :: 3.9
Classifier: Programming Language :: Python :: 3.10
Classifier: Programming Language :: Python :: 3.11
Classifier: Programming Language :: Python :: 3.12
Classifier: Programming Language :: Python :: 3.13
Classifier: Topic :: Software Development :: Libraries :: Python Modules
Provides-Extra: test
Requires-Dist: chardet (>=5.2.0,<6.0.0)
Requires-Dist: omegaconf (>=2.3.0,<3.0.0)
Project-URL: Repository, https://github.com/svdimchenko/ski-lint/
